[{"info": "hello", "user_id": 8, "links": ["<link rel='parent' title='project' href='http://crowd.globalfishingwatch.org/api/project/23'/>", "<link rel='parent' title='task' href='http://crowd.globalfishingwatch.org/api/task/6089'/>"], "task_id": 6089, "created": "2016-05-13T17:28:42.130911", "finish_time": "2016-05-13T17:40:43.855852", "calibration": null, "user_ip": null, "link": "<link rel='self' title='taskrun' href='http://crowd.globalfishingwatch.org/api/taskrun/6026'/>", "timeout": null, "project_id": 23, "id": 6026}]